bentoml_plugins/arize/__init__.py
bentoml_plugins/arize/py.typed
bentoml_plugins/arize/version.py
bentoml_plugins_arize-0.1.0.dist-info/METADATA
bentoml_plugins_arize-0.1.0.dist-info/WHEEL
bentoml_plugins_arize-0.1.0.dist-info/licenses/LICENSE
bentoml_plugins_arize-0.1.0.dist-info/RECORD
