Metadata-Version: 2.1
Name: bentoml-plugins-arize
Version: 0.1.0
Summary: BentoML Monitoring Arize Plugin
Project-URL: Homepage, https://github.com/bentoml/bentoml_plugins/tree/main/monitoring/bentoml-plugins-arize
Author-email: BentoML Team <contact@bentoml.com>
License: Apache-2.0
License-File: LICENSE
Keywords: AI,BentoML,MLOps,Model Deployment,Model Serving
Classifier: Development Status :: 4 - Beta
Classifier: Intended Audience :: Developers
Classifier: Intended Audience :: Education
Classifier: Intended Audience :: Science/Research
Classifier: License :: OSI Approved :: Apache Software License
Classifier: Operating System :: OS Independent
Classifier: Programming Language :: Python :: 3
Classifier: Programming Language :: Python :: 3 :: Only
Classifier: Programming Language :: Python :: 3.7
Classifier: Programming Language :: Python :: 3.8
Classifier: Programming Language :: Python :: 3.9
Classifier: Programming Language :: Python :: 3.10
Classifier: Programming Language :: Python :: 3.11
Classifier: Topic :: Scientific/Engineering :: Artificial Intelligence
Classifier: Topic :: Software Development :: Libraries
Requires-Python: >=3.7
Requires-Dist: arize>=5.2.0
Requires-Dist: bentoml>=1.0.10
Provides-Extra: test
Requires-Dist: pytest; extra == 'test'
Requires-Dist: pytest-asyncio; extra == 'test'
Requires-Dist: pytest-cov; extra == 'test'
Requires-Dist: pytest-xdist; extra == 'test'
